LeosToDoList/__init__.py
LeosToDoList/back_end.py
LeosToDoList/front_end.py
LeosToDoList/main.py
leostodolist-1.0.0.dist-info/METADATA
leostodolist-1.0.0.dist-info/WHEEL
leostodolist-1.0.0.dist-info/entry_points.txt
leostodolist-1.0.0.dist-info/RECORD
