Metadata-Version: 2.3
Name: LeosToDoList
Version: 1.0.0
Summary: to-do-list manager
Author: Leo Iwanetzki
Author-email: leo@iwanetzki.de
License: MIT
Requires-Python: >=3.10
Requires-Dist: babel>=2.16.0
Requires-Dist: tkcalendar>=1.6.1
